p3lib/__init__.py
p3lib/ate.py
p3lib/bokeh_auth.py
p3lib/bokeh_gui.py
p3lib/boot_manager.py
p3lib/conduit.py
p3lib/database_if.py
p3lib/file_io.py
p3lib/helper.py
p3lib/json_networking.py
p3lib/launcher.py
p3lib/login.html
p3lib/mqtt_rpc.py
p3lib/netif.py
p3lib/netplotly.py
p3lib/ngt.py
p3lib/ngt3.py
p3lib/pconfig.py
p3lib/ssh.py
p3lib/table_plot.py
p3lib/uio.py
p3lib/windows_app.py
p3lib-1.1.148.dist-info/LICENSE
p3lib-1.1.148.dist-info/METADATA
p3lib-1.1.148.dist-info/WHEEL
p3lib-1.1.148.dist-info/RECORD
